{"info": {"id": "FXOptionVanilla_03", "group": null, "counterparty": null, "businessUnit0": null, "businessUnit1": null, "businessUnit2": null, "businessUnit3": null, "businessUnit4": null, "trader": null, "collateralCurrency": null, "csa": null}, "description": {"currency": "USD", "foreignCurrency": "EUR", "domesticCurrency": "USD", "exerciseType": "european", "callPut": "put", "buySell": "sell", "strike": 1.0778, "notional": 45000000.0, "notionalCurrency": "EUR", "settlementDate": "2017-01-05", "maturityDate": "2016-12-30", "premium": {"currency": "EUR", "structure": {"2016-05-05": 10000.0}}}}